pputils
