Metadata-Version: 1.0
Name: pputils
Version: 1.1
Summary: utils by python
Home-page: UNKNOWN
Author: Peng Jun
Author-email: UNKNOWN
License: PJ
Platform: UNKNOWN
